Metadata-Version: 1.0
Name: AudioLib
Version: 1.0.0b1
Summary: A high level sounds api for python
Home-page: https://github.com/HelloWorld-py/AudioLib
Author: Jacob Tsekrekos
Author-email: jdtsekrekos@live.com
License: MIT
Keywords: audio sound media wav player
Platform: UNKNOWN
